oil_reservoir_synthesizer/__init__.py
oil_reservoir_synthesizer/_oil_simulator.py
oil_reservoir_synthesizer/_perlin.py
oil_reservoir_synthesizer/_prime_generator.py
oil_reservoir_synthesizer/_shaped_perlin.py
oil_reservoir_synthesizer-0.1.0.dist-info/COPYING
oil_reservoir_synthesizer-0.1.0.dist-info/METADATA
oil_reservoir_synthesizer-0.1.0.dist-info/WHEEL
oil_reservoir_synthesizer-0.1.0.dist-info/top_level.txt
oil_reservoir_synthesizer-0.1.0.dist-info/RECORD
