Metadata-Version: 2.1
Name: oil-reservoir-synthesizer
Version: 0.1.0
Summary: A generator for synthetic oil reservoir values
Author-email: Equinor <fg_sib-scout@equinor.com>
Maintainer-email: Eivind Jahren <ejah@equinor.com>
License: GPL-3.0
Project-URL: Homepage, https://github.com/equinor/oil_reservoir_synthesizer
Project-URL: Repository, https://github.com/equinor/oil_reservoir_synthesizer
Project-URL: Bug Tracker, https://github.com/equinor/oil_reservoir_synthesizer/issues
Classifier: Development Status :: 1 - Planning
Classifier: License :: OSI Approved :: GNU Lesser General Public License v3 or later (LGPLv3+)
Classifier: Programming Language :: Python
Classifier: Programming Language :: Python :: 3.7
Classifier: Programming Language :: Python :: 3.8
Classifier: Programming Language :: Python :: 3.9
Classifier: Programming Language :: Python :: 3.10
Requires-Dist: numpy
Provides-Extra: dev
Requires-Dist: pytest ; extra == 'dev'
Requires-Dist: tox ; extra == 'dev'
Requires-Dist: pre-commit ; extra == 'dev'
